mantra/__init__.py
mantra/datasets.py
mantra/lex_to_json.py
mantra/set_property.py
mantra/transforms.py
mantra/utils.py
mantra_dataset-0.0.16.dist-info/licenses/LICENSE.md
mantra_dataset-0.0.16.dist-info/METADATA
mantra_dataset-0.0.16.dist-info/WHEEL
mantra_dataset-0.0.16.dist-info/top_level.txt
mantra_dataset-0.0.16.dist-info/RECORD
