Metadata-Version: 2.4
Name: mantra-dataset
Version: 0.0.16
Summary: A package for working with higher-order datasets like manifold triangulations.
Author-email: Ernst Röell <ernst.roeell@helmholtz-munich.de>, Bastian Rieck <bastian.rieck@helmholtz-munich.de>
Maintainer-email: Ernst Röell <ernst.roeell@helmholtz-munich.de>
License: Copyright (c) 2024 Ernst Röell, Daniel Bin Schmid and Bastian Rieck
Project-URL: documentation, https://aidos.group/mantra/
Project-URL: repository, https://github.com/aidos-lab/mantra
Project-URL: issues, https://github.com/aidos-lab/mantra/issues
Project-URL: changelog, https://github.com/aidos-lab/mantra/blob/main/CHANGELOG.md
Keywords: topology,deep learning,tda,tdl,topological machine learning,topological data analysis,topological deep learning
Classifier: Development Status :: 4 - Beta
Classifier: Programming Language :: Python
Requires-Python: >=3.8
License-File: LICENSE.md
Requires-Dist: black>=22.0
Requires-Dist: numpy
Requires-Dist: torch
Requires-Dist: torch_geometric
Dynamic: license-file
